{
    "robot": [
        {"id":"hello","msg":"Hello, my name is Xiao Zhi"},
        {"id":"你好","msg":"在呢！有什么可以帮到你"},
        {"id":"你好?","msg":"在呢！有什么可以帮到你"},
        {"id":"你好？","msg":"在呢！有什么可以帮到你"},
        {"id": "早上好", "msg": "早上好，小智为你播报"},
        {"id": "中午好", "msg": "中午好，小智为你播报"},
        {"id": "下午好", "msg": "下午好，小智为你播报"},
        {"id": "晚上好", "msg": "晚上好，小智为你播报"},
        {"id": "你在干什么", "msg": "我在看着你呀！"},
        {"id": "你是男的还是女的", "msg": "你希望我是男的还是女的呀！"},
        {"id": "您的妈妈叫什么名字", "msg": "我的妈妈叫小华"},
        {"id": "您的爸爸叫什么名字", "msg": "我的爸爸叫小能"},
        {"id": "您的妈妈是谁", "msg": "我的妈妈是给伟大的人"},
        {"id": "你在干什么啊！", "msg": "我在等你跟我聊天呢"},
        {"id": "你喜欢我吗？", "msg": "当然喜欢你了"},
        {"id": "你喜欢我吗?", "msg": "当然喜欢你了"},
        {"id": "你吃饭了吗", "msg": "吃完了，你呢！"},
        {"id": "你吃饭了吗?", "msg": "吃完了，你呢！"},
        {"id": "你吃饭了吗？", "msg": "吃完了，你呢！"},
        {"id": "小智同学", "msg": "我在呢！有什么可以帮到你"},
        {"id": "你叫什么名字", "msg": "我叫小智，有什么可以帮到你"},
        {"id": "你叫什么名字?", "msg": "我叫小智，有什么可以帮到你"},
        {"id": "你叫什么名字？", "msg": "我叫小智，有什么可以帮到你"}
    ]
}
